spotifywebapi/__init__.py
spotifywebapi/api_helper.py
spotifywebapi/configuration.py
spotifywebapi/spotifywebapi_client.py
spotifywebapi/controllers/__init__.py
spotifywebapi/controllers/albums_controller.py
spotifywebapi/controllers/artists_controller.py
spotifywebapi/controllers/audiobooks_controller.py
spotifywebapi/controllers/base_controller.py
spotifywebapi/controllers/categories_controller.py
spotifywebapi/controllers/chapters_controller.py
spotifywebapi/controllers/episodes_controller.py
spotifywebapi/controllers/genres_controller.py
spotifywebapi/controllers/markets_controller.py
spotifywebapi/controllers/o_auth_authorization_controller.py
spotifywebapi/controllers/player_controller.py
spotifywebapi/controllers/playlists_controller.py
spotifywebapi/controllers/search_controller.py
spotifywebapi/controllers/shows_controller.py
spotifywebapi/controllers/tracks_controller.py
spotifywebapi/controllers/users_controller.py
spotifywebapi/exceptions/__init__.py
spotifywebapi/exceptions/api_exception.py
spotifywebapi/exceptions/bad_request_exception.py
spotifywebapi/exceptions/forbidden_exception.py
spotifywebapi/exceptions/not_found_exception.py
spotifywebapi/exceptions/o_auth_provider_exception.py
spotifywebapi/exceptions/too_many_requests_exception.py
spotifywebapi/exceptions/unauthorized_exception.py
spotifywebapi/http/__init__.py
spotifywebapi/http/api_response.py
spotifywebapi/http/http_call_back.py
spotifywebapi/http/http_method_enum.py
spotifywebapi/http/http_request.py
spotifywebapi/http/http_response.py
spotifywebapi/http/auth/__init__.py
spotifywebapi/http/auth/o_auth_2.py
spotifywebapi/models/__init__.py
spotifywebapi/models/album_base.py
spotifywebapi/models/album_group_enum.py
spotifywebapi/models/album_object.py
spotifywebapi/models/album_restriction_object.py
spotifywebapi/models/album_type_enum.py
spotifywebapi/models/artist_discography_album_object.py
spotifywebapi/models/artist_object.py
spotifywebapi/models/audio_analysis_object.py
spotify_api_sdk-1.0.0.dist-info/LICENSE
spotify_api_sdk-1.0.0.dist-info/METADATA
spotify_api_sdk-1.0.0.dist-info/WHEEL
spotify_api_sdk-1.0.0.dist-info/top_level.txt
spotify_api_sdk-1.0.0.dist-info/RECORD
