Metadata-Version: 2.1
Name: spotify-api-sdk
Version: 1.0.0
Summary: You can use Spotify's Web API to discover music and podcasts, manage your Spotify library, control audio playback, and much more. Browse our available Web API endpoints using the sidebar at left, or via the navigation bar on top of this page on smaller screens.
Author-email: developer sdksio <developer+sdksio@apimatic.io>
Project-URL: Documentation, https://spotify-poc.pages.dev/
Keywords: Spotify,Apimatic,SDK,API
Requires-Python: >=3.7
License-File: LICENSE
Requires-Dist: apimatic-core >=0.2.15,~=0.2.0
Requires-Dist: apimatic-core-interfaces >=0.1.5,~=0.1.0
Requires-Dist: apimatic-requests-client-adapter >=0.1.6,~=0.1.0
Provides-Extra: testutils
Requires-Dist: pytest >=7.2.2 ; extra == 'testutils'
